flywheel_bids_tools/__init__.py
flywheel_bids_tools/group_query.py
flywheel_bids_tools/query_bids.py
flywheel_bids_tools/query_gears.py
flywheel_bids_tools/ungroup_query.py
flywheel_bids_tools/upload_bids.py
flywheel_bids_tools-0.0.4.dist-info/METADATA
flywheel_bids_tools-0.0.4.dist-info/RECORD
flywheel_bids_tools-0.0.4.dist-info/WHEEL
flywheel_bids_tools-0.0.4.dist-info/entry_points.txt
flywheel_bids_tools-0.0.4.dist-info/top_level.txt
